{
    "url": "https://api.github.com/repos/pallets/flask/issues/1018",
    "repository_url": "https://api.github.com/repos/pallets/flask",
    "labels_url": "https://api.github.com/repos/pallets/flask/issues/1018/labels{/name}",
    "comments_url": "https://api.github.com/repos/pallets/flask/issues/1018/comments",
    "events_url": "https://api.github.com/repos/pallets/flask/issues/1018/events",
    "html_url": "https://github.com/pallets/flask/pull/1018",
    "id": 31278724,
    "node_id": "MDExOlB1bGxSZXF1ZXN0MTQ2MjQ5NTI=",
    "number": 1018,
    "title": "Clarified that the code is meant to be saved as a file called hello.py.",
    "user": {
        "login": "fureigh",
        "id": 1244599,
        "node_id": "MDQ6VXNlcjEyNDQ1OTk=",
        "avatar_url": "https://avatars2.githubusercontent.com/u/1244599?v=4",
        "gravatar_id": "",
        "url": "https://api.github.com/users/fureigh",
        "html_url": "https://github.com/fureigh",
        "followers_url": "https://api.github.com/users/fureigh/followers",
        "following_url": "https://api.github.com/users/fureigh/following{/other_user}",
        "gists_url": "https://api.github.com/users/fureigh/gists{/gist_id}",
        "starred_url": "https://api.github.com/users/fureigh/starred{/owner}{/repo}",
        "subscriptions_url": "https://api.github.com/users/fureigh/subscriptions",
        "organizations_url": "https://api.github.com/users/fureigh/orgs",
        "repos_url": "https://api.github.com/users/fureigh/repos",
        "events_url": "https://api.github.com/users/fureigh/events{/privacy}",
        "received_events_url": "https://api.github.com/users/fureigh/received_events",
        "type": "User",
        "site_admin": false
    },
    "labels": [],
    "state": "closed",
    "locked": false,
    "assignee": null,
    "assignees": [],
    "milestone": null,
    "comments": 1,
    "created_at": "2014-04-10T20:37:30Z",
    "updated_at": "2014-06-12T10:38:14Z",
    "closed_at": "2014-05-07T19:51:22Z",
    "author_association": "NONE",
    "pull_request": {
        "url": "https://api.github.com/repos/pallets/flask/pulls/1018",
        "html_url": "https://github.com/pallets/flask/pull/1018",
        "diff_url": "https://github.com/pallets/flask/pull/1018.diff",
        "patch_url": "https://github.com/pallets/flask/pull/1018.patch"
    },
    "body": "Clarified that the code is meant to be saved as a file called hello.py.\n",
    "comments_inline": [
        {
            "url": "https://api.github.com/repos/pallets/flask/issues/comments/42982182",
            "html_url": "https://github.com/pallets/flask/pull/1018#issuecomment-42982182",
            "issue_url": "https://api.github.com/repos/pallets/flask/issues/1018",
            "id": 42982182,
            "node_id": "MDEyOklzc3VlQ29tbWVudDQyOTgyMTgy",
            "user": {
                "login": "fureigh",
                "id": 1244599,
                "node_id": "MDQ6VXNlcjEyNDQ1OTk=",
                "avatar_url": "https://avatars2.githubusercontent.com/u/1244599?v=4",
                "gravatar_id": "",
                "url": "https://api.github.com/users/fureigh",
                "html_url": "https://github.com/fureigh",
                "followers_url": "https://api.github.com/users/fureigh/followers",
                "following_url": "https://api.github.com/users/fureigh/following{/other_user}",
                "gists_url": "https://api.github.com/users/fureigh/gists{/gist_id}",
                "starred_url": "https://api.github.com/users/fureigh/starred{/owner}{/repo}",
                "subscriptions_url": "https://api.github.com/users/fureigh/subscriptions",
                "organizations_url": "https://api.github.com/users/fureigh/orgs",
                "repos_url": "https://api.github.com/users/fureigh/repos",
                "events_url": "https://api.github.com/users/fureigh/events{/privacy}",
                "received_events_url": "https://api.github.com/users/fureigh/received_events",
                "type": "User",
                "site_admin": false
            },
            "created_at": "2014-05-13T16:58:48Z",
            "updated_at": "2014-05-13T16:58:48Z",
            "author_association": "NONE",
            "body": "@mitsuhiko Thanks for reviewing this. The fix in 2639a23 doesn't quite address the issue I was trying to fix, though. I was trying to clarify on the front page of http://flask.pocoo.org that the code beneath \"Flask is Fun\" is meant to be saved as a file called hello.py. Can you take another look?\n"
        }
    ]
}