{
    "url": "https://api.github.com/repos/pallets/flask/issues/2568",
    "repository_url": "https://api.github.com/repos/pallets/flask",
    "labels_url": "https://api.github.com/repos/pallets/flask/issues/2568/labels{/name}",
    "comments_url": "https://api.github.com/repos/pallets/flask/issues/2568/comments",
    "events_url": "https://api.github.com/repos/pallets/flask/issues/2568/events",
    "html_url": "https://github.com/pallets/flask/pull/2568",
    "id": 284372674,
    "node_id": "MDExOlB1bGxSZXF1ZXN0MTYwMDA1MzI0",
    "number": 2568,
    "title": "Fixed Typo",
    "user": {
        "login": "ghost",
        "id": 10137,
        "node_id": "MDQ6VXNlcjEwMTM3",
        "avatar_url": "https://avatars3.githubusercontent.com/u/10137?v=4",
        "gravatar_id": "",
        "url": "https://api.github.com/users/ghost",
        "html_url": "https://github.com/ghost",
        "followers_url": "https://api.github.com/users/ghost/followers",
        "following_url": "https://api.github.com/users/ghost/following{/other_user}",
        "gists_url": "https://api.github.com/users/ghost/gists{/gist_id}",
        "starred_url": "https://api.github.com/users/ghost/starred{/owner}{/repo}",
        "subscriptions_url": "https://api.github.com/users/ghost/subscriptions",
        "organizations_url": "https://api.github.com/users/ghost/orgs",
        "repos_url": "https://api.github.com/users/ghost/repos",
        "events_url": "https://api.github.com/users/ghost/events{/privacy}",
        "received_events_url": "https://api.github.com/users/ghost/received_events",
        "type": "User",
        "site_admin": false
    },
    "labels": [],
    "state": "closed",
    "locked": true,
    "assignee": null,
    "assignees": [],
    "milestone": null,
    "comments": 1,
    "created_at": "2017-12-24T16:50:42Z",
    "updated_at": "2017-12-27T18:08:58Z",
    "closed_at": "2017-12-27T18:07:17Z",
    "author_association": "NONE",
    "pull_request": {
        "url": "https://api.github.com/repos/pallets/flask/pulls/2568",
        "html_url": "https://github.com/pallets/flask/pull/2568",
        "diff_url": "https://github.com/pallets/flask/pull/2568.diff",
        "patch_url": "https://github.com/pallets/flask/pull/2568.patch"
    },
    "body": "Fixed Typo in the tutorials\r\nChanged when -> how\r\n",
    "comments_inline": [
        {
            "url": "https://api.github.com/repos/pallets/flask/issues/comments/353795281",
            "html_url": "https://github.com/pallets/flask/pull/2568#issuecomment-353795281",
            "issue_url": "https://api.github.com/repos/pallets/flask/issues/2568",
            "id": 353795281,
            "node_id": "MDEyOklzc3VlQ29tbWVudDM1Mzc5NTI4MQ==",
            "user": {
                "login": "ThiefMaster",
                "id": 179599,
                "node_id": "MDQ6VXNlcjE3OTU5OQ==",
                "avatar_url": "https://avatars1.githubusercontent.com/u/179599?v=4",
                "gravatar_id": "",
                "url": "https://api.github.com/users/ThiefMaster",
                "html_url": "https://github.com/ThiefMaster",
                "followers_url": "https://api.github.com/users/ThiefMaster/followers",
                "following_url": "https://api.github.com/users/ThiefMaster/following{/other_user}",
                "gists_url": "https://api.github.com/users/ThiefMaster/gists{/gist_id}",
                "starred_url": "https://api.github.com/users/ThiefMaster/starred{/owner}{/repo}",
                "subscriptions_url": "https://api.github.com/users/ThiefMaster/subscriptions",
                "organizations_url": "https://api.github.com/users/ThiefMaster/orgs",
                "repos_url": "https://api.github.com/users/ThiefMaster/repos",
                "events_url": "https://api.github.com/users/ThiefMaster/events{/privacy}",
                "received_events_url": "https://api.github.com/users/ThiefMaster/received_events",
                "type": "User",
                "site_admin": false
            },
            "created_at": "2017-12-24T17:23:48Z",
            "updated_at": "2017-12-24T17:24:27Z",
            "author_association": "MEMBER",
            "body": "Stop this dumb nitpicking war right now, thanks. This is not a kindergarten playground."
        }
    ]
}