{
    "url": "https://api.github.com/repos/pallets/flask/issues/2891",
    "repository_url": "https://api.github.com/repos/pallets/flask",
    "labels_url": "https://api.github.com/repos/pallets/flask/issues/2891/labels{/name}",
    "comments_url": "https://api.github.com/repos/pallets/flask/issues/2891/comments",
    "events_url": "https://api.github.com/repos/pallets/flask/issues/2891/events",
    "html_url": "https://github.com/pallets/flask/issues/2891",
    "id": 353087747,
    "node_id": "MDU6SXNzdWUzNTMwODc3NDc=",
    "number": 2891,
    "title": "request.get_json(force=True) not working as expected",
    "user": {
        "login": "a2x",
        "id": 7684726,
        "node_id": "MDQ6VXNlcjc2ODQ3MjY=",
        "avatar_url": "https://avatars0.githubusercontent.com/u/7684726?v=4",
        "gravatar_id": "",
        "url": "https://api.github.com/users/a2x",
        "html_url": "https://github.com/a2x",
        "followers_url": "https://api.github.com/users/a2x/followers",
        "following_url": "https://api.github.com/users/a2x/following{/other_user}",
        "gists_url": "https://api.github.com/users/a2x/gists{/gist_id}",
        "starred_url": "https://api.github.com/users/a2x/starred{/owner}{/repo}",
        "subscriptions_url": "https://api.github.com/users/a2x/subscriptions",
        "organizations_url": "https://api.github.com/users/a2x/orgs",
        "repos_url": "https://api.github.com/users/a2x/repos",
        "events_url": "https://api.github.com/users/a2x/events{/privacy}",
        "received_events_url": "https://api.github.com/users/a2x/received_events",
        "type": "User",
        "site_admin": false
    },
    "labels": [],
    "state": "closed",
    "locked": false,
    "assignee": null,
    "assignees": [],
    "milestone": null,
    "comments": 2,
    "created_at": "2018-08-22T19:16:55Z",
    "updated_at": "2018-08-24T02:50:56Z",
    "closed_at": "2018-08-24T02:50:56Z",
    "author_association": "NONE",
    "body": "requesting **without** {'Content-Type': 'application/json'} \r\nrequest.get_json(force=True) returns nothing (not as expected)\r\nrequest.get_json(force=False) returns None (not as expected)\r\n\r\nrequesting **with** {'Content-Type': 'application/json'} \r\nrequest.get_json(force=True) returns the JSON parsed to dict\r\nrequest.get_json(force=False) returns the JSON parsed to dict\r\n\r\nExpected behavior: \r\nShouldn't request.get_json(force=True) like mentioned in the docs \"Ignore the mimetype and always try to parse JSON.\"?\r\n\r\nthx, and keep up the great work\r\n\r\n",
    "comments_inline": [
        {
            "url": "https://api.github.com/repos/pallets/flask/issues/comments/415342530",
            "html_url": "https://github.com/pallets/flask/issues/2891#issuecomment-415342530",
            "issue_url": "https://api.github.com/repos/pallets/flask/issues/2891",
            "id": 415342530,
            "node_id": "MDEyOklzc3VlQ29tbWVudDQxNTM0MjUzMA==",
            "user": {
                "login": "vastpeng",
                "id": 15377472,
                "node_id": "MDQ6VXNlcjE1Mzc3NDcy",
                "avatar_url": "https://avatars1.githubusercontent.com/u/15377472?v=4",
                "gravatar_id": "",
                "url": "https://api.github.com/users/vastpeng",
                "html_url": "https://github.com/vastpeng",
                "followers_url": "https://api.github.com/users/vastpeng/followers",
                "following_url": "https://api.github.com/users/vastpeng/following{/other_user}",
                "gists_url": "https://api.github.com/users/vastpeng/gists{/gist_id}",
                "starred_url": "https://api.github.com/users/vastpeng/starred{/owner}{/repo}",
                "subscriptions_url": "https://api.github.com/users/vastpeng/subscriptions",
                "organizations_url": "https://api.github.com/users/vastpeng/orgs",
                "repos_url": "https://api.github.com/users/vastpeng/repos",
                "events_url": "https://api.github.com/users/vastpeng/events{/privacy}",
                "received_events_url": "https://api.github.com/users/vastpeng/received_events",
                "type": "User",
                "site_admin": false
            },
            "created_at": "2018-08-23T08:53:38Z",
            "updated_at": "2018-08-23T08:53:38Z",
            "author_association": "NONE",
            "body": "I try it, but it works fine.\r\n\r\ncan you show some details? like what you post and how do it."
        },
        {
            "url": "https://api.github.com/repos/pallets/flask/issues/comments/415634365",
            "html_url": "https://github.com/pallets/flask/issues/2891#issuecomment-415634365",
            "issue_url": "https://api.github.com/repos/pallets/flask/issues/2891",
            "id": 415634365,
            "node_id": "MDEyOklzc3VlQ29tbWVudDQxNTYzNDM2NQ==",
            "user": {
                "login": "greyli",
                "id": 12967000,
                "node_id": "MDQ6VXNlcjEyOTY3MDAw",
                "avatar_url": "https://avatars3.githubusercontent.com/u/12967000?v=4",
                "gravatar_id": "",
                "url": "https://api.github.com/users/greyli",
                "html_url": "https://github.com/greyli",
                "followers_url": "https://api.github.com/users/greyli/followers",
                "following_url": "https://api.github.com/users/greyli/following{/other_user}",
                "gists_url": "https://api.github.com/users/greyli/gists{/gist_id}",
                "starred_url": "https://api.github.com/users/greyli/starred{/owner}{/repo}",
                "subscriptions_url": "https://api.github.com/users/greyli/subscriptions",
                "organizations_url": "https://api.github.com/users/greyli/orgs",
                "repos_url": "https://api.github.com/users/greyli/repos",
                "events_url": "https://api.github.com/users/greyli/events{/privacy}",
                "received_events_url": "https://api.github.com/users/greyli/received_events",
                "type": "User",
                "site_admin": false
            },
            "created_at": "2018-08-24T02:44:29Z",
            "updated_at": "2018-08-24T02:44:29Z",
            "author_association": "MEMBER",
            "body": "Please provide [a Minimal, Complete, and Verifiable example](https://stackoverflow.com/help/mcve)."
        }
    ]
}