{
    "url": "https://api.github.com/repos/pallets/flask/issues/3010",
    "repository_url": "https://api.github.com/repos/pallets/flask",
    "labels_url": "https://api.github.com/repos/pallets/flask/issues/3010/labels{/name}",
    "comments_url": "https://api.github.com/repos/pallets/flask/issues/3010/comments",
    "events_url": "https://api.github.com/repos/pallets/flask/issues/3010/events",
    "html_url": "https://github.com/pallets/flask/issues/3010",
    "id": 386321801,
    "node_id": "MDU6SXNzdWUzODYzMjE4MDE=",
    "number": 3010,
    "title": "Requests stop being processed when basic auth is expected but not provided",
    "user": {
        "login": "sajohn2",
        "id": 8323044,
        "node_id": "MDQ6VXNlcjgzMjMwNDQ=",
        "avatar_url": "https://avatars2.githubusercontent.com/u/8323044?v=4",
        "gravatar_id": "",
        "url": "https://api.github.com/users/sajohn2",
        "html_url": "https://github.com/sajohn2",
        "followers_url": "https://api.github.com/users/sajohn2/followers",
        "following_url": "https://api.github.com/users/sajohn2/following{/other_user}",
        "gists_url": "https://api.github.com/users/sajohn2/gists{/gist_id}",
        "starred_url": "https://api.github.com/users/sajohn2/starred{/owner}{/repo}",
        "subscriptions_url": "https://api.github.com/users/sajohn2/subscriptions",
        "organizations_url": "https://api.github.com/users/sajohn2/orgs",
        "repos_url": "https://api.github.com/users/sajohn2/repos",
        "events_url": "https://api.github.com/users/sajohn2/events{/privacy}",
        "received_events_url": "https://api.github.com/users/sajohn2/received_events",
        "type": "User",
        "site_admin": false
    },
    "labels": [],
    "state": "closed",
    "locked": false,
    "assignee": null,
    "assignees": [],
    "milestone": null,
    "comments": 3,
    "created_at": "2018-11-30T19:36:02Z",
    "updated_at": "2018-11-30T23:32:13Z",
    "closed_at": "2018-11-30T19:49:37Z",
    "author_association": "NONE",
    "body": "### Expected Behavior\r\n\r\nSteps to reproducing the problem:\r\n1. Make a request that provides any basic auth\r\n2. Make a request without basic auth\r\n3. Make a request that provides any basic auth (this request is not being processed)\r\n\r\nI would expect the server to continue processing requests.\r\n\r\n```python\r\nfrom flask import Flask, request, jsonify\r\n\r\napp = Flask(__name__)\r\n\r\n\r\n@app.route('/')\r\n@app.route('/api')\r\ndef api():\r\n    auth = request.authorization\r\n    if not auth:\r\n        return jsonify({'status': 'NO AUTH'})\r\n    return jsonify({'status': 'GOT AUTH'})\r\n```\r\n\r\n### Actual Behavior\r\n\r\nThe server seems to hang on request 3.\r\n\r\n### Environment\r\n\r\n* Python version: 3.6.6\r\n* Flask version: 1.0.2\r\n* Werkzeug version: 0.14.1\r\n\r\nFull environment info:\r\nMacOS 10.13.6\r\nPython 3.6.6 (Anaconda)\r\n\r\nAll packages:\r\n```text\r\naniso8601==4.0.1\r\nClick==7.0\r\nFlask==1.0.2\r\nFlask-RESTful==0.3.6\r\nitsdangerous==1.1.0\r\nJinja2==2.10\r\nMarkupSafe==1.1.0\r\npytz==2018.7\r\nsix==1.11.0\r\nWerkzeug==0.14.1\r\n```\r\n",
    "comments_inline": [
        {
            "url": "https://api.github.com/repos/pallets/flask/issues/comments/443319139",
            "html_url": "https://github.com/pallets/flask/issues/3010#issuecomment-443319139",
            "issue_url": "https://api.github.com/repos/pallets/flask/issues/3010",
            "id": 443319139,
            "node_id": "MDEyOklzc3VlQ29tbWVudDQ0MzMxOTEzOQ==",
            "user": {
                "login": "davidism",
                "id": 1242887,
                "node_id": "MDQ6VXNlcjEyNDI4ODc=",
                "avatar_url": "https://avatars1.githubusercontent.com/u/1242887?v=4",
                "gravatar_id": "",
                "url": "https://api.github.com/users/davidism",
                "html_url": "https://github.com/davidism",
                "followers_url": "https://api.github.com/users/davidism/followers",
                "following_url": "https://api.github.com/users/davidism/following{/other_user}",
                "gists_url": "https://api.github.com/users/davidism/gists{/gist_id}",
                "starred_url": "https://api.github.com/users/davidism/starred{/owner}{/repo}",
                "subscriptions_url": "https://api.github.com/users/davidism/subscriptions",
                "organizations_url": "https://api.github.com/users/davidism/orgs",
                "repos_url": "https://api.github.com/users/davidism/repos",
                "events_url": "https://api.github.com/users/davidism/events{/privacy}",
                "received_events_url": "https://api.github.com/users/davidism/received_events",
                "type": "User",
                "site_admin": false
            },
            "created_at": "2018-11-30T19:49:37Z",
            "updated_at": "2018-11-30T19:49:37Z",
            "author_association": "MEMBER",
            "body": "I can't reproduce your issue. I made three requests as described and the server did not hang.\r\n\r\n```python\r\nimport requests\r\n\r\nprint(requests.get(\"http://127.0.0.1:5000/\", auth=(\"user\", \"pass\")).text)\r\nprint(requests.get(\"http://127.0.0.1:5000/\").text)\r\nprint(requests.get(\"http://127.0.0.1:5000/\", auth=(\"user\", \"pass\")).text)\r\n```"
        },
        {
            "url": "https://api.github.com/repos/pallets/flask/issues/comments/443356396",
            "html_url": "https://github.com/pallets/flask/issues/3010#issuecomment-443356396",
            "issue_url": "https://api.github.com/repos/pallets/flask/issues/3010",
            "id": 443356396,
            "node_id": "MDEyOklzc3VlQ29tbWVudDQ0MzM1NjM5Ng==",
            "user": {
                "login": "sajohn2",
                "id": 8323044,
                "node_id": "MDQ6VXNlcjgzMjMwNDQ=",
                "avatar_url": "https://avatars2.githubusercontent.com/u/8323044?v=4",
                "gravatar_id": "",
                "url": "https://api.github.com/users/sajohn2",
                "html_url": "https://github.com/sajohn2",
                "followers_url": "https://api.github.com/users/sajohn2/followers",
                "following_url": "https://api.github.com/users/sajohn2/following{/other_user}",
                "gists_url": "https://api.github.com/users/sajohn2/gists{/gist_id}",
                "starred_url": "https://api.github.com/users/sajohn2/starred{/owner}{/repo}",
                "subscriptions_url": "https://api.github.com/users/sajohn2/subscriptions",
                "organizations_url": "https://api.github.com/users/sajohn2/orgs",
                "repos_url": "https://api.github.com/users/sajohn2/repos",
                "events_url": "https://api.github.com/users/sajohn2/events{/privacy}",
                "received_events_url": "https://api.github.com/users/sajohn2/received_events",
                "type": "User",
                "site_admin": false
            },
            "created_at": "2018-11-30T22:17:12Z",
            "updated_at": "2018-11-30T22:17:12Z",
            "author_association": "NONE",
            "body": "This was happening when switching from Chrome to Postman. It looks like there are reports of similar issues with Chrome and its unrelated to the code itself. Running in threaded mode seems to fix the problem. Still not my favorite fix.\r\n\r\nhttps://stackoverflow.com/questions/42519629/flask-not-processing-other-http-requests-after-chrome-browser-accesses-the-web-s\r\nhttps://github.com/pallets/flask/issues/2169\r\n"
        },
        {
            "url": "https://api.github.com/repos/pallets/flask/issues/comments/443371506",
            "html_url": "https://github.com/pallets/flask/issues/3010#issuecomment-443371506",
            "issue_url": "https://api.github.com/repos/pallets/flask/issues/3010",
            "id": 443371506,
            "node_id": "MDEyOklzc3VlQ29tbWVudDQ0MzM3MTUwNg==",
            "user": {
                "login": "davidism",
                "id": 1242887,
                "node_id": "MDQ6VXNlcjEyNDI4ODc=",
                "avatar_url": "https://avatars1.githubusercontent.com/u/1242887?v=4",
                "gravatar_id": "",
                "url": "https://api.github.com/users/davidism",
                "html_url": "https://github.com/davidism",
                "followers_url": "https://api.github.com/users/davidism/followers",
                "following_url": "https://api.github.com/users/davidism/following{/other_user}",
                "gists_url": "https://api.github.com/users/davidism/gists{/gist_id}",
                "starred_url": "https://api.github.com/users/davidism/starred{/owner}{/repo}",
                "subscriptions_url": "https://api.github.com/users/davidism/subscriptions",
                "organizations_url": "https://api.github.com/users/davidism/orgs",
                "repos_url": "https://api.github.com/users/davidism/repos",
                "events_url": "https://api.github.com/users/davidism/events{/privacy}",
                "received_events_url": "https://api.github.com/users/davidism/received_events",
                "type": "User",
                "site_admin": false
            },
            "created_at": "2018-11-30T23:32:13Z",
            "updated_at": "2018-11-30T23:32:13Z",
            "author_association": "MEMBER",
            "body": "Threaded mode is the default."
        }
    ]
}