{
    "url": "https://api.github.com/repos/pallets/flask/issues/3342",
    "repository_url": "https://api.github.com/repos/pallets/flask",
    "labels_url": "https://api.github.com/repos/pallets/flask/issues/3342/labels{/name}",
    "comments_url": "https://api.github.com/repos/pallets/flask/issues/3342/comments",
    "events_url": "https://api.github.com/repos/pallets/flask/issues/3342/events",
    "html_url": "https://github.com/pallets/flask/issues/3342",
    "id": 484859560,
    "node_id": "MDU6SXNzdWU0ODQ4NTk1NjA=",
    "number": 3342,
    "title": "Using getlist for files is never empty?",
    "user": {
        "login": "aaveidt",
        "id": 5781080,
        "node_id": "MDQ6VXNlcjU3ODEwODA=",
        "avatar_url": "https://avatars3.githubusercontent.com/u/5781080?v=4",
        "gravatar_id": "",
        "url": "https://api.github.com/users/aaveidt",
        "html_url": "https://github.com/aaveidt",
        "followers_url": "https://api.github.com/users/aaveidt/followers",
        "following_url": "https://api.github.com/users/aaveidt/following{/other_user}",
        "gists_url": "https://api.github.com/users/aaveidt/gists{/gist_id}",
        "starred_url": "https://api.github.com/users/aaveidt/starred{/owner}{/repo}",
        "subscriptions_url": "https://api.github.com/users/aaveidt/subscriptions",
        "organizations_url": "https://api.github.com/users/aaveidt/orgs",
        "repos_url": "https://api.github.com/users/aaveidt/repos",
        "events_url": "https://api.github.com/users/aaveidt/events{/privacy}",
        "received_events_url": "https://api.github.com/users/aaveidt/received_events",
        "type": "User",
        "site_admin": false
    },
    "labels": [],
    "state": "closed",
    "locked": false,
    "assignee": null,
    "assignees": [],
    "milestone": null,
    "comments": 1,
    "created_at": "2019-08-24T20:31:26Z",
    "updated_at": "2019-08-24T21:07:18Z",
    "closed_at": "2019-08-24T21:07:03Z",
    "author_association": "NONE",
    "body": "I want to get file list from form by using:\r\n\r\n`photos = request.files.getlist(\"photo\")\r\n`\r\nHowever if i haven't select anything, the photos value is never be [] like other fields.\r\n\r\nSo the way to check for empty field is failed:\r\n\r\n```\r\nif not photos:\r\n   pass\r\n```\r\nThe result for empty form is:\r\n` [<FileStorage: '' ('application/octet-stream')>]`\r\n\r\nHow do i get rid of it?",
    "comments_inline": [
        {
            "url": "https://api.github.com/repos/pallets/flask/issues/comments/524580272",
            "html_url": "https://github.com/pallets/flask/issues/3342#issuecomment-524580272",
            "issue_url": "https://api.github.com/repos/pallets/flask/issues/3342",
            "id": 524580272,
            "node_id": "MDEyOklzc3VlQ29tbWVudDUyNDU4MDI3Mg==",
            "user": {
                "login": "davidism",
                "id": 1242887,
                "node_id": "MDQ6VXNlcjEyNDI4ODc=",
                "avatar_url": "https://avatars1.githubusercontent.com/u/1242887?v=4",
                "gravatar_id": "",
                "url": "https://api.github.com/users/davidism",
                "html_url": "https://github.com/davidism",
                "followers_url": "https://api.github.com/users/davidism/followers",
                "following_url": "https://api.github.com/users/davidism/following{/other_user}",
                "gists_url": "https://api.github.com/users/davidism/gists{/gist_id}",
                "starred_url": "https://api.github.com/users/davidism/starred{/owner}{/repo}",
                "subscriptions_url": "https://api.github.com/users/davidism/subscriptions",
                "organizations_url": "https://api.github.com/users/davidism/orgs",
                "repos_url": "https://api.github.com/users/davidism/repos",
                "events_url": "https://api.github.com/users/davidism/events{/privacy}",
                "received_events_url": "https://api.github.com/users/davidism/received_events",
                "type": "User",
                "site_admin": false
            },
            "created_at": "2019-08-24T21:07:03Z",
            "updated_at": "2019-08-24T21:07:18Z",
            "author_association": "MEMBER",
            "body": "Duplicate of #3130 \r\n\r\n> `request.files` always has whatever is submitted. You can do `request.files[\"secondfile\"].filename == \"\"`, or look at its size. But it was still submitted, just with an empty filename and no data. Again, that's just what HTML forms do.\r\n\r\nhttps://github.com/pallets/flask/issues/3130#issuecomment-476765447"
        }
    ]
}